pyidenticounter.py
pyidenticounter-0.4.0.dist-info/entry_points.txt
pyidenticounter-0.4.0.dist-info/LICENSE
pyidenticounter-0.4.0.dist-info/WHEEL
pyidenticounter-0.4.0.dist-info/METADATA
pyidenticounter-0.4.0.dist-info/RECORD
